meu_cli.py
meu_cli-0.2.dist-info/METADATA
meu_cli-0.2.dist-info/WHEEL
meu_cli-0.2.dist-info/entry_points.txt
meu_cli-0.2.dist-info/top_level.txt
meu_cli-0.2.dist-info/RECORD
